util/__init__.py
util/utils.py
util_gfsilveira-0.1.dist-info/METADATA
util_gfsilveira-0.1.dist-info/WHEEL
util_gfsilveira-0.1.dist-info/top_level.txt
util_gfsilveira-0.1.dist-info/RECORD
